bw_functional/__init__.py
bw_functional/allocation.py
bw_functional/convert.py
bw_functional/database.py
bw_functional/edge_classes.py
bw_functional/node_classes.py
bw_functional/update.py
bw_functional-0b97.dist-info/licenses/LICENSE
bw_functional-0b97.dist-info/METADATA
bw_functional-0b97.dist-info/WHEEL
bw_functional-0b97.dist-info/top_level.txt
bw_functional-0b97.dist-info/RECORD
